zntrack/__init__.py
zntrack/abc.py
zntrack/add.py
zntrack/apply.py
zntrack/config.py
zntrack/converter.py
zntrack/deployment.py
zntrack/exceptions.py
zntrack/from_rev.py
zntrack/group.py
zntrack/node.py
zntrack/project.py
zntrack/state.py
zntrack/cli/__init__.py
zntrack/cli/cli.py
zntrack/cli/mlflow.py
zntrack/examples/__init__.py
zntrack/examples/nodes.py
zntrack/fields/__init__.py
zntrack/fields/base.py
zntrack/fields/deps.py
zntrack/fields/outs_and_metrics.py
zntrack/fields/params.py
zntrack/fields/plots.py
zntrack/fields/x_path.py
zntrack/plugins/__init__.py
zntrack/plugins/base.py
zntrack/plugins/aim_plugin/__init__.py
zntrack/plugins/dvc_plugin/__init__.py
zntrack/plugins/dvc_plugin/dvc.py
zntrack/plugins/dvc_plugin/params.py
zntrack/plugins/mlflow_plugin/__init__.py
zntrack/utils/__init__.py
zntrack/utils/filesystem.py
zntrack/utils/finalize.py
zntrack/utils/import_handler.py
zntrack/utils/list_nodes.py
zntrack/utils/lockfile.py
zntrack/utils/misc.py
zntrack/utils/node_wd.py
zntrack/utils/state.py
zntrack-0.8.10.dist-info/METADATA
zntrack-0.8.10.dist-info/WHEEL
zntrack-0.8.10.dist-info/entry_points.txt
zntrack-0.8.10.dist-info/licenses/LICENSE
zntrack-0.8.10.dist-info/RECORD
