Metadata-Version: 2.4
Name: zntrack
Version: 0.8.10
Summary: Create, Run and Benchmark DVC Pipelines in Python
Project-URL: Repository, https://github.com/zincware/zntrack
Project-URL: Releases, https://github.com/zincware/zntrack/releases
Project-URL: Documentation, https://zntrack.readthedocs.io
Project-URL: Discord, https://discord.gg/7ncfwhsnm4
Author-email: Fabian Zills <fzills@icp.uni-stuttgart.de>
License-Expression: Apache-2.0
License-File: LICENSE
Keywords: collaboration,data-science,data-version-control,machine-learning,reproducibility
Requires-Python: >=3.10
Requires-Dist: dvc>=3.60.0
Requires-Dist: pandas>=2.2.3
Requires-Dist: pyyaml>=6.0.2
Requires-Dist: tqdm>=4.67.1
Requires-Dist: typer>=0.15.1
Requires-Dist: znfields>=0.1.2
Requires-Dist: znflow>=0.2.5
Requires-Dist: znjson>=0.2.6
